{
  "error.400.bad_request": "Nieprawidłowe żądanie",
  "error.401.unauthorized": "Wymagane uwierzytelnienie",
  "error.402.payment_required": "Wymagana płatność",
  "error.403.forbidden": "Nie masz uprawnień do wykonania tej akcji",
  "error.404.not_found": "Nie znaleziono żądanego zasobu",
  "error.405.method_not_allowed": "Metoda niedozwolona",
  "error.406.not_acceptable": "Nieakceptowalny format odpowiedzi",
  "error.408.request_timeout": "Przekroczono limit czasu żądania",
  "error.409.conflict": "Zasób już istnieje",
  "error.410.gone": "Zasób został trwale usunięty",
  "error.413.payload_too_large": "Treść żądania jest zbyt duża",
  "error.415.unsupported_media_type": "Nieobsługiwany typ mediów",
  "error.422.unprocessable_entity": "Nie można przetworzyć żądania",
  "error.423.locked": "Zasób jest zablokowany",
  "error.429.too_many_requests": "Zbyt wiele żądań. Spróbuj ponownie później.",
  "error.429.rate_limit": "Zbyt wiele prób. Spróbuj ponownie za {retry_after_minutes} min.",
  "error.400.validation_error": "Błąd walidacji",
  "error.400.expected_list": "Oczekiwano listy elementów",
  "error.400.invalid_ad_id": "Nieprawidłowy identyfikator ogłoszenia",
  "error.404.ad_not_found": "Nie znaleziono ogłoszenia",
  "error.400.field.required": "Pole {field} jest wymagane",
  "error.400.field.null": "Pole {field} nie może mieć wartości null",
  "error.400.field.blank": "Pole {field} nie może być puste",
  "error.400.field.max_length": "Pole {field} może mieć najwyżej {max_length} znaków",
  "error.400.field.min_length": "Pole {field} musi mieć co najmniej {min_length} znaków",
  "error.400.field.max_value": "Wartość pola {field} może wynosić najwyżej {max_value}",
  "error.400.field.min_value": "Wartość pola {field} musi wynosić co najmniej {min_value}",
  "error.400.field.invalid": "Pole {field} jest nieprawidłowe",
  "error.400.field.invalid_choice": "Wartość pola {field} nie jest prawidłowym wyborem",
  "error.400.field.does_not_exist": "Pole {field} nie istnieje",
  "error.400.field.unique": "Wartość pola {field} musi być unikalna",
  "error.500.internal": "Coś poszło nie tak",
  "error.403.verification_required": "Wymagana dodatkowa weryfikacja",
  "error.400.verification_invalid_factor": "Ten sposób weryfikacji jest niedostępny",
  "error.400.verification_failed": "Weryfikacja nie powiodła się",
  "error.404.verification_challenge_not_found": "Nie znaleziono żądania weryfikacji lub wygasło",
  "error.423.verification_locked": "Zbyt wiele nieudanych prób — weryfikacja zablokowana",
  "error.401.invalid_credentials": "Nieprawidłowe dane logowania",
  "error.401.account_disabled": "Konto użytkownika jest wyłączone",
  "error.422.blocked": "Konto tymczasowo zablokowane. Spróbuj ponownie za {retry_after_minutes} min.",
  "error.400.code_expired": "Kod weryfikacyjny wygasł. Poproś o nowy.",
  "error.400.invalid_code": "Nieprawidłowy kod weryfikacyjny",
  "error.400.invalid_code_attempts": "Nieprawidłowy kod weryfikacyjny. Pozostało prób: {attempts_remaining}.",
  "error.500.send_failed": "Nie udało się wysłać kodu weryfikacyjnego",
  "error.409.email_taken": "Ten adres e-mail jest już zarejestrowany na innym koncie.",
  "error.409.email_reserved": "Ten adres e-mail jest zarezerwowany przez inne oczekujące żądanie zmiany.",
  "error.409.phone_taken": "Ten numer telefonu jest już zarejestrowany na innym koncie.",
  "error.409.phone_reserved": "Ten numer telefonu jest zarezerwowany przez inne oczekujące żądanie zmiany.",
  "error.409.username_taken": "Ta nazwa użytkownika jest już zajęta.",
  "error.400.token_required": "Token jest wymagany",
  "error.401.token_revoked": "Token został unieważniony",
  "error.401.token_invalid": "Nieprawidłowy token",
  "error.400.oauth_failed": "Nie udało się uwierzytelnić u dostawcy OAuth",
  "error.400.oauth_fields_required": "Pola provider i access_token są wymagane",
  "error.400.credentials_required": "Nazwa użytkownika/e-mail i hasło są wymagane",
  "error.401.refresh_invalid": "Nieprawidłowy lub wygasły token odświeżania",
  "error.401.refresh_not_provided": "Nie podano tokenu odświeżania",
  "error.401.refresh_revoked": "Token został unieważniony",
  "error.401.user_not_found": "Nie znaleziono użytkownika",
  "error.400.not_available": "Ta wartość jest już zarejestrowana lub zarezerwowana.",
  "error.400.no_current_value": "Brak bieżącej wartości na tym koncie.",
  "error.400.invalid_change_token": "Nieprawidłowy lub wygasły token zmiany.",
  "error.404.change_not_found": "Nie znaleziono żądania zmiany.",
  "error.400.phone_required": "Numer telefonu jest wymagany.",
  "error.400.email_required": "Adres e-mail jest wymagany.",
  "error.400.invalid_phone_format": "Nieprawidłowy format numeru telefonu",
  "error.400.invalid_phone": "Nieprawidłowy numer telefonu",
  "error.400.phone_too_long": "Numer telefonu jest zbyt długi",
  "error.400.passwords_dont_match": "Hasła nie są zgodne",
  "error.400.email_or_phone_required": "Wymagany jest adres e-mail lub numer telefonu",
  "error.400.email_or_phone_not_both": "Podaj adres e-mail albo numer telefonu, nie oba",
  "error.400.wrong_password": "Błędne hasło.",
  "error.400.password_already_set": "Hasło jest już ustawione. Użyj opcji zmiany hasła.",
  "error.400.no_password": "Nie ustawiono hasła. Najpierw ustaw hasło.",
  "error.400.no_verified_contact": "Brak zweryfikowanego adresu e-mail lub numeru telefonu na tym koncie.",
  "error.400.invalid_method": "Nieprawidłowa lub niedostępna metoda dla tego konta.",
  "error.404.user_for_reset": "Nie znaleziono konta z tym adresem e-mail lub numerem telefonu.",
  "error.403.mock_otp_admin": "Uwierzytelnianie oparte na OTP jest wyłączone dla kont administratorów w trybie mock.",
  "error.404.qr_not_found": "Nie znaleziono kodu QR lub wygasł.",
  "error.400.qr_expired": "Kod QR wygasł.",
  "error.400.qr_fulfilled": "Kod QR został już użyty.",
  "error.400.qr_type_required": "Typ kodu QR jest wymagany (session_share lub login_request).",
  "error.401.qr_auth_required": "Wymagane uwierzytelnienie, aby wygenerować kod QR session_share.",
  "error.409.qr_account_conflict": "Na tym urządzeniu zalogowane jest już inne konto.",
  "error.403.qr_device_mismatch": "Ten kod QR należy do innego urządzenia.",
  "error.403.qr_unauth_scan": "Tego kodu QR nie można zeskanować na niezalogowanym urządzeniu.",
  "error.400.code_required": "Kod weryfikacyjny jest wymagany.",
  "error.400.totp_not_pending": "Brak oczekującej konfiguracji TOTP. Najpierw wywołaj /totp/setup/.",
  "error.403.step_up_required": "Ta akcja wymaga weryfikacji TOTP. Najpierw uzyskaj token step-up.",
  "error.423.account_locked": "Konto tymczasowo zablokowane z powodu zbyt wielu nieudanych prób. Spróbuj ponownie za {retry_after_minutes} min.",
  "error.400.invalid_redirect_url": "redirect_url musi być ścieżką względną zaczynającą się od / — bezwzględne adresy URL są niedozwolone.",
  "error.400.magic_link_invalid": "Link do logowania jest nieprawidłowy lub wygasł.",
  "error.429.magic_link_rate": "Zbyt wiele żądań linku do logowania. Spróbuj ponownie później.",
  "error.400.passkey_invalid": "Weryfikacja klucza dostępu nie powiodła się.",
  "error.400.passkey_challenge_expired": "Żądanie weryfikacji klucza dostępu wygasło. Spróbuj ponownie.",
  "error.409.passkey_already_registered": "Ten klucz dostępu jest już zarejestrowany.",
  "error.400.last_auth_method": "Nie można usunąć ostatniej metody uwierzytelniania.",
  "error.404.passkey_not_found": "Nie znaleziono klucza dostępu.",
  "error.404.sso_org_not_found": "Nie znaleziono organizacji.",
  "error.400.sso_not_configured": "SSO nie jest skonfigurowane dla tej organizacji.",
  "error.400.sso_invalid_response": "Nieprawidłowa odpowiedź SSO od dostawcy tożsamości.",
  "error.403.sso_required": "To konto musi logować się przez SSO. Użyj linku SSO swojej organizacji.",
  "error.409.sso_org_slug_taken": "Organizacja z tym identyfikatorem (slug) już istnieje.",
  "error.400.captcha_invalid": "Weryfikacja captcha nie powiodła się. Spróbuj ponownie.",
  "error.400.captcha_required": "Token captcha jest wymagany.",
  "error.404.wallet_not_found": "Nie znaleziono portfela",
  "error.404.subscription_not_found": "Nie znaleziono subskrypcji",
  "error.404.transaction_not_found": "Nie znaleziono transakcji",
  "error.402.insufficient_credits": "Niewystarczająca liczba kredytów",
  "error.400.invalid_package": "Nieprawidłowy pakiet kredytów",
  "error.400.invalid_plan": "Nieprawidłowy plan subskrypcji",
  "error.400.amount_invalid": "Kwota musi być dodatnią liczbą całkowitą",
  "error.400.invalid_stripe_signature": "Nieprawidłowy podpis webhooka Stripe",
  "error.400.invalid_webhook_payload": "Nieprawidłowa treść webhooka Stripe",
  "error.403.forbidden_billing": "Brak dostępu: nie można zarządzać tym kontem rozliczeniowym",
  "error.409.duplicate_webhook_event": "Zdarzenie Stripe zostało już przetworzone",
  "error.400.no_file": "Nie przesłano pliku",
  "error.400.invalid_format": "Nieobsługiwany format pliku",
  "error.413.file_too_large": "Plik jest zbyt duży",
  "error.400.invalid_hash": "Nieprawidłowy hash pliku",
  "error.400.invalid_image_type": "Nieprawidłowy typ obrazu",
  "error.404.no_images": "Nie znaleziono przetworzonych obrazów",
  "error.400.file_hash_required": "Parametr file_hash jest wymagany",
  "error.400.missing_fields": "Brakuje wymaganych pól",
  "error.400.file_type_not_allowed": "Niedozwolony typ pliku",
  "error.409.gdpr.export_cooldown": "W ciągu ostatnich 30 dni zażądano już eksportu danych.",
  "error.409.gdpr.closure_already_pending": "Zamknięcie konta jest już w toku.",
  "error.409.gdpr.legal_hold": "Dane konta są objęte blokadą prawną i nie mogą zostać usunięte.",
  "error.404.gdpr.no_active_closure": "Nie znaleziono oczekującego zamknięcia konta.",
  "error.404.gdpr.export_not_found": "Nie znaleziono żądania eksportu.",
  "error.410.gdpr.download_expired": "Link do pobrania wygasł.",
  "error.425.gdpr.export_not_ready": "Eksport jest wciąż przygotowywany.",
  "error.400.invalid_platform": "Platforma musi być jedną z: ios, android, web.",
  "error.404.token_not_found": "Nie znaleziono tokenu urządzenia.",
  "error.404.profile_not_found": "Nie znaleziono profilu",
  "error.400.cannot_follow_self": "Nie możesz obserwować samego siebie",
  "error.400.cannot_block_self": "Nie możesz zablokować samego siebie",
  "error.400.display_name_too_short": "Wyświetlana nazwa musi mieć co najmniej 2 znaki",
  "error.400.display_name_forbidden_chars": "Wyświetlana nazwa zawiera niedozwolone znaki",
  "error.400.display_name_emoji": "Wyświetlana nazwa nie może zawierać emoji",
  "error.400.display_name_invisible_chars": "Wyświetlana nazwa zawiera niewidoczne znaki",
  "error.400.invalid_currency": "Nieprawidłowy kod waluty",
  "error.400.invalid_avatar_format": "Nieprawidłowy format odwołania do awatara. Oczekiwano: avatar/<hash>",
  "error.400.avatar_not_found": "Nie znaleziono awatara w CDN",
  "error.404.workspace_not_found": "Nie znaleziono przestrzeni roboczej",
  "error.404.member_not_found": "Nie znaleziono członka w tej przestrzeni roboczej",
  "error.404.invitation_not_found": "Nie znaleziono zaproszenia",
  "error.403.forbidden_workspace": "Nie masz dostępu do tej przestrzeni roboczej",
  "error.403.last_owner_cannot_be_removed": "Nie można usunąć ostatniego właściciela; najpierw przekaż własność",
  "error.400.workspace_slug_taken": "Identyfikator (slug) przestrzeni roboczej jest już zajęty",
  "error.400.already_workspace_member": "Użytkownik jest już członkiem tej przestrzeni roboczej",
  "error.400.invitation_expired": "Zaproszenie wygasło",
  "error.400.invitation_already_used": "Zaproszenie zostało już wykorzystane",
  "error.400.invitation_revoked": "Zaproszenie zostało unieważnione",
  "error.400.invalid_role": "Nieprawidłowa rola",
  "notification.otp_code.subject": "Twój kod weryfikacyjny {company_name}: {code}",
  "notification.otp_code.heading": "Twój kod weryfikacyjny",
  "notification.otp_code.body": "Użyj poniższego kodu, aby potwierdzić swoją tożsamość:",
  "notification.otp_code.warning": "Nie udostępniaj nikomu tego kodu. Jeśli ta prośba nie pochodzi od Ciebie, możesz spokojnie zignorować tę wiadomość.",
  "notification.otp_code.expiry": "Ten kod wygaśnie za {expiry_minutes} min.",
  "notification.otp_code.sms": "Twój kod {company_name}: {code}. Wygasa za {expiry_minutes} min.",
  "notification.auth_change_requested.subject": "Zażądano zmiany danych logowania",
  "notification.auth_change_requested.heading": "Zażądano zmiany",
  "notification.auth_change_requested.body": "Zażądano zmiany: {change_type}. Nowa wartość ({change_type}): {masked_new_value}. Zmiana zostanie zakończona: {scheduled_date}.",
  "notification.auth_change_requested.warning": "Jeśli ta zmiana nie pochodzi od Ciebie, natychmiast skontaktuj się z pomocą techniczną.",
  "notification.auth_change_requested.sms": "{company_name}: zażądano zmiany ({change_type}). Zakończenie: {scheduled_date}. Skontaktuj się z pomocą, jeśli to nie Ty.",
  "notification.auth_change_requested.push_title": "Zażądano zmiany danych logowania",
  "notification.auth_change_requested.push_body": "Zmiana ({change_type}) zostanie zakończona {scheduled_date}.",
  "notification.auth_change_reminder.subject": "Przypomnienie: zmiana ({change_type}) za {days_remaining} dni",
  "notification.auth_change_reminder.heading": "Przypomnienie o zmianie",
  "notification.auth_change_reminder.body": "Za {days_remaining} dni wartość {change_type} zostanie zmieniona na {masked_new_value}.",
  "notification.auth_change_reminder.warning": "Jeśli ta zmiana nie pochodzi od Ciebie, skontaktuj się z pomocą techniczną.",
  "notification.auth_change_reminder.sms": "{company_name}: za {days_remaining} dni {change_type} zmieni się na {masked_new_value}. Skontaktuj się z pomocą, jeśli to nie Ty.",
  "notification.auth_change_reminder.push_title": "Zmiana ({change_type}) za {days_remaining} dni",
  "notification.auth_change_reminder.push_body": "Wartość {change_type} zostanie zmieniona na {masked_new_value}.",
  "notification.auth_change_urgent.subject": "PILNE: zmiana ({change_type}) jutro",
  "notification.auth_change_urgent.heading": "Zmiana jutro",
  "notification.auth_change_urgent.body": "Wartość {change_type} zostanie zmieniona JUTRO ({scheduled_date}). To ostatnia szansa, aby anulować zmianę.",
  "notification.auth_change_urgent.warning": "Po tej zmianie do logowania będzie potrzebna nowa wartość {change_type}.",
  "notification.auth_change_urgent.sms": "PILNE: {company_name} — zmiana ({change_type}) jutro ({scheduled_date}). Ostatnia szansa na anulowanie!",
  "notification.auth_change_urgent.push_title": "PILNE: zmiana ({change_type}) jutro",
  "notification.auth_change_urgent.push_body": "Ostatnia szansa, aby anulować zmianę ({change_type}).",
  "notification.auth_change_completed.subject": "Pomyślnie zmieniono: {change_type}",
  "notification.auth_change_completed.heading": "Zmiana zakończona",
  "notification.auth_change_completed.body": "Wartość {change_type} na Twoim koncie została pomyślnie zmieniona.",
  "notification.auth_change_completed.warning": "Jeśli ta zmiana nie została przez Ciebie autoryzowana, natychmiast skontaktuj się z pomocą techniczną.",
  "notification.auth_change_completed.sms": "{company_name}: zmieniono {change_type}. Skontaktuj się z pomocą, jeśli to nie Ty.",
  "notification.auth_change_completed.push_title": "Zmieniono: {change_type}",
  "notification.auth_change_completed.push_body": "Wartość {change_type} na Twoim koncie została zaktualizowana.",
  "notification.gdpr.export_ready.subject": "Twój eksport danych jest gotowy",
  "notification.gdpr.export_ready.heading": "Twój eksport danych jest gotowy",
  "notification.gdpr.export_ready.body": "Zamówiona kopia Twoich danych osobowych jest gotowa do pobrania. Link do pobrania jest ważny przez ograniczony czas.",
  "notification.gdpr.export_ready.cta": "Pobierz moje dane",
  "notification.gdpr.export_ready.warning": "Jeśli żądanie eksportu nie pochodzi od Ciebie, natychmiast skontaktuj się z pomocą techniczną.",
  "notification.gdpr.inactivity_warning.subject": "Twoje konto zostanie zamknięte za {days_remaining} dni",
  "notification.gdpr.inactivity_warning.heading": "Tęsknimy za Tobą",
  "notification.gdpr.inactivity_warning.body": "Twoje konto od dłuższego czasu jest nieaktywne. Za {days_remaining} dni zostanie zamknięte, a Twoje dane usunięte, chyba że zalogujesz się ponownie.",
  "notification.gdpr.inactivity_warning.warning": "Wystarczy jedno logowanie, aby konto pozostało aktywne.",
  "notification.gdpr.inactivity_closed.subject": "Twoje konto zostało zamknięte",
  "notification.gdpr.inactivity_closed.heading": "Twoje konto zostało zamknięte",
  "notification.gdpr.inactivity_closed.body": "Twoje konto zostało zamknięte z powodu długotrwałej nieaktywności, a Twoje dane osobowe zostały usunięte zgodnie z naszą polityką przechowywania danych.",
  "notification.gdpr.inactivity_closed.warning": "Jeśli uważasz, że to pomyłka, skontaktuj się z naszym zespołem pomocy.",
  "notification.workspace.invitation.subject": "Zaproszenie do {workspace_name}",
  "notification.workspace.invitation.heading": "Zaproszenie do przestrzeni roboczej",
  "notification.workspace.invitation.body": "{inviter_name} zaprasza Cię do dołączenia do przestrzeni roboczej „{workspace_name}”.",
  "notification.workspace.invitation.cta": "Przyjmij zaproszenie",
  "notification.new_message.subject": "Nowa wiadomość od {sender_name}",
  "notification.new_message.heading": "Nowa wiadomość od {sender_name}",
  "notification.new_message.body": "Masz nową wiadomość dotyczącą „{listing_title}”.",
  "notification.new_message.cta": "Otwórz czat",
  "notification.new_message.push_title": "Nowa wiadomość od {sender_name}",
  "notification.new_message.push_body": "{sender_name}: {message_preview}",
  "notification.report_reviewed.subject": "Twoje zgłoszenie zostało rozpatrzone",
  "notification.report_reviewed.heading": "Twoje zgłoszenie zostało rozpatrzone",
  "notification.report_reviewed.body": "Dziękujemy za zgłoszenie ogłoszenia. Po weryfikacji podjęliśmy odpowiednie działania.",
  "notification.report_reviewed.cta": "Zobacz szczegóły",
  "notification.report_reviewed.push_title": "Zgłoszenie rozpatrzone",
  "notification.report_reviewed.push_body": "Twoje zgłoszenie zostało rozpatrzone i podjęto działania.",
  "notification.listing_expiring.subject": "Twoje ogłoszenie wkrótce wygaśnie",
  "notification.listing_expiring.heading": "Twoje ogłoszenie wygasa",
  "notification.listing_expiring.body": "Twoje ogłoszenie „{listing_title}” zostanie wycofane z publikacji za {days_remaining} dni. Możesz włączyć automatyczne wznawianie, aby pozostało aktywne.",
  "notification.listing_expiring.cta": "Zobacz ogłoszenie",
  "notification.listing_expiring.push_title": "Ogłoszenie wygasa",
  "notification.listing_expiring.push_body": "„{listing_title}” wygasa za {days_remaining} dni.",
  "notification.listing_blocked.subject": "Twoje ogłoszenie zostało zablokowane",
  "notification.listing_blocked.heading": "Twoje ogłoszenie zostało zablokowane",
  "notification.listing_blocked.body": "Twoje ogłoszenie „{listing_title}” zostało zablokowane za naruszenie zasad {company_name}.",
  "notification.listing_blocked.cta": "Dowiedz się więcej",
  "notification.listing_blocked.warning": "Jeśli uważasz, że to pomyłka, skontaktuj się z naszym zespołem pomocy.",
  "notification.listing_blocked.push_title": "Ogłoszenie zablokowane",
  "notification.listing_blocked.push_body": "„{listing_title}” zostało zablokowane za naruszenie zasad.",
  "notification.magic_link_login.subject": "Twój link do logowania w {company_name}",
  "notification.magic_link_login.heading": "Zaloguj się do {company_name}",
  "notification.magic_link_login.body": "Kliknij poniższy przycisk, aby się zalogować. Link wygasa za 15 minut i może być użyty tylko raz.",
  "notification.magic_link_login.cta": "Zaloguj się",
  "notification.magic_link_login.warning": "Jeśli ta prośba nie pochodzi od Ciebie, możesz spokojnie zignorować tę wiadomość.",
  "notification.new_device_login.subject": "Nowe logowanie na Twoje konto",
  "notification.new_device_login.heading": "Wykryto nowe logowanie",
  "notification.new_device_login.body": "Na Twoje konto zalogowano się z nowego urządzenia.\n\nUrządzenie: {device_name}\nIP: {ip_address}",
  "notification.new_device_login.cta": "Zabezpiecz moje konto",
  "notification.new_device_login.warning": "Jeśli to Ty, nie musisz nic robić. Jeśli nie rozpoznajesz tego logowania, natychmiast zabezpiecz swoje konto.",
  "notification.suspicious_login.subject": "Wykryto podejrzane logowanie",
  "notification.suspicious_login.heading": "Wykryto podejrzane logowanie",
  "notification.suspicious_login.body": "Na Twoim koncie wykryto logowanie z nieznanej lokalizacji.\n\nUrządzenie: {device_name}\nIP: {ip_address}",
  "notification.suspicious_login.cta": "To nie ja — unieważnij wszystkie sesje",
  "notification.suspicious_login.warning": "Jeśli to Ty, nie musisz nic robić. Jeśli nie, natychmiast kliknij przycisk powyżej, aby unieważnić wszystkie sesje.",
  "notification.all_sessions_revoked.subject": "Unieważniono wszystkie sesje",
  "notification.all_sessions_revoked.heading": "Wszystkie sesje zostały unieważnione",
  "notification.all_sessions_revoked.body": "Wszystkie aktywne sesje na Twoim koncie zostały unieważnione. Wylogowano Cię ze wszystkich urządzeń.",
  "notification.all_sessions_revoked.warning": "Jeśli ta akcja nie została zainicjowana przez Ciebie, natychmiast zresetuj hasło.",
  "notification.footer.legal": "© {company_year} {company_name}",
  "notification.footer.address": "{company_address}",
  "notification.footer.consent": "Otrzymujesz tę wiadomość, ponieważ zgodziłeś(-aś) się na otrzymywanie wiadomości od {company_name}.",
  "notification.footer.unsubscribe": "Wypisz się",
  "notification.footer.manage": "Zarządzaj powiadomieniami"
}
